src/__init__.py
src/frontend/css/service_engine.scss
src/genie_cli/__init__.py
src/genie_cli/__main__.py
src/genie_cli/app.py
src/genie_cli/config.py
src/genie_cli/constants.py
src/genie_cli/locations.py
src/genie_cli/models.py
src/genie_cli/prompts/behaviour_prompts.py
src/genie_cli/prompts/round_code_examples.py
src/genie_cli/prompts/rounds_prompts.py
src/genie_cli/runtime_config.py
src/genie_cli/screens/chat_details.py
src/genie_cli/screens/chat_screen.py
src/genie_cli/screens/code_generation_screen.py
src/genie_cli/screens/fsm_generation_screen.py
src/genie_cli/screens/home_screen.py
src/genie_cli/screens/login_screen.py
src/genie_cli/screens/scaffold_screen.py
src/genie_cli/states/states.py
src/genie_cli/widgets/agent_is_typing.py
src/genie_cli/widgets/app_header.py
src/genie_cli/widgets/chat.py
src/genie_cli/widgets/chat_header.py
src/genie_cli/widgets/chat_options.py
src/genie_cli/widgets/chatbox.py
src/genie_cli/widgets/fsm_widget.py
src/genie_cli/widgets/login_widget.py
src/genie_cli/widgets/prompt_input.py
src/genie_cli/widgets/scaffold_chat.py
src/genie_cli/widgets/scaffold_widget.py
src/genie_cli/widgets/scaffolding_options.py
src/genie_cli/widgets/skill_options.py
src/genie_cli/widgets/welcome.py
src/scaffolding_client/constants.py
src/scaffolding_client/models.py
src/scaffolding_client/scaffold.py
src/scaffolding_client/utils.py
genie_cli-0.1.0a3.dist-info/LICENSE
genie_cli-0.1.0a3.dist-info/METADATA
genie_cli-0.1.0a3.dist-info/WHEEL
genie_cli-0.1.0a3.dist-info/entry_points.txt
genie_cli-0.1.0a3.dist-info/RECORD
