Metadata-Version: 2.1
Name: genie-cli
Version: 0.1.0a3
Summary: A CLI tool from Valory to interact with the Genie service to generate Olas autonomous services from natural language
Author: Keshav Mishra
Author-email: keshav.mishra0298@gmail.com
Requires-Python: >=3.11,<4.0
Classifier: Programming Language :: Python :: 3
Classifier: Programming Language :: Python :: 3.11
Classifier: Programming Language :: Python :: 3.12
Requires-Dist: certifi (>=2024.8.30,<2025.0.0)
Requires-Dist: click (>=8.1.7,<9.0.0)
Requires-Dist: click-default-group (>=1.2.4,<2.0.0)
Requires-Dist: humanize (>=4.9.0,<5.0.0)
Requires-Dist: litellm (>=1.40.9,<2.0.0)
Requires-Dist: pyperclip (>=1.9.0,<2.0.0)
Requires-Dist: python-dotenv (>=1.0.1,<2.0.0)
Requires-Dist: requests (>=2.32.3,<3.0.0)
Requires-Dist: rich (>=13.7.1,<14.0.0)
Requires-Dist: textual (>=0.67.1,<0.68.0)
Requires-Dist: types-requests (>=2.32.0.20240907,<3.0.0.0)
Requires-Dist: xdg-base-dirs (>=6.0.1,<7.0.0)
